README.md
setup.cfg
setup.py
context_helpers/__init__.py
context_helpers.egg-info/PKG-INFO
context_helpers.egg-info/SOURCES.txt
context_helpers.egg-info/dependency_links.txt
context_helpers.egg-info/requires.txt
context_helpers.egg-info/top_level.txt